wsgi_shim/__init__.py
wsgi_shim/__main__.py
wsgi_shim/hello_world.py
wsgi_shim/wsgi_shim.py
wsgi_shim/templates/config.toml
wsgi_shim-0.1.0.dist-info/LICENSE
wsgi_shim-0.1.0.dist-info/METADATA
wsgi_shim-0.1.0.dist-info/WHEEL
wsgi_shim-0.1.0.dist-info/entry_points.txt
wsgi_shim-0.1.0.dist-info/top_level.txt
wsgi_shim-0.1.0.dist-info/RECORD
