Metadata-Version: 2.1
Name: wsgi-shim
Version: 0.1.0
Summary: WSGI shim for when you have limited web log access
Author-email: Scott Karlin <scott@cs.princeton.edu>
Project-URL: Home Page, https://csguide.cs.princeton.edu/software/python-wsgi
Classifier: Programming Language :: Python :: 3
Classifier: Programming Language :: Python :: 3.11
Classifier: Programming Language :: Python :: 3.12
Classifier: License :: OSI Approved :: MIT License
Classifier: Operating System :: POSIX
Classifier: Development Status :: 5 - Production/Stable
Classifier: Topic :: Internet :: WWW/HTTP :: WSGI
Classifier: Intended Audience :: Developers
Requires-Python: >=3.11
License-File: LICENSE
Provides-Extra: build
Requires-Dist: build ; extra == 'build'
Requires-Dist: twine ; extra == 'build'
Requires-Dist: packaging ; extra == 'build'
Provides-Extra: ci
Requires-Dist: pytest >=7.4 ; extra == 'ci'
Requires-Dist: twine ; extra == 'ci'
Requires-Dist: packaging ; extra == 'ci'
Requires-Dist: ruff ; extra == 'ci'
Requires-Dist: whitenoise >=6.6.0 ; extra == 'ci'
Requires-Dist: Flask >=3.0 ; extra == 'ci'
Requires-Dist: Django >=5.0 ; extra == 'ci'
Provides-Extra: dev
Requires-Dist: build ; extra == 'dev'
Requires-Dist: twine ; extra == 'dev'
Requires-Dist: packaging ; extra == 'dev'
Requires-Dist: pre-commit >=3.4 ; extra == 'dev'
Requires-Dist: pytest >=7.4 ; extra == 'dev'
Requires-Dist: pytest-cov >=4.1 ; extra == 'dev'
Requires-Dist: coverage >=7.3 ; extra == 'dev'
Requires-Dist: whitenoise >=6.6.0 ; extra == 'dev'
Requires-Dist: Flask >=3.0 ; extra == 'dev'
Requires-Dist: Django >=5.0 ; extra == 'dev'
Provides-Extra: tests
Requires-Dist: pytest >=7.4 ; extra == 'tests'
